mcp_nixos/__init__.py
mcp_nixos/__main__.py
mcp_nixos/server.py
mseep_mcp_nixos-1.0.0.dist-info/licenses/LICENSE
tests/__init__.py
tests/conftest.py
tests/test_advanced_integration.py
tests/test_channel_handling.py
tests/test_dynamic_channels.py
tests/test_edge_cases.py
tests/test_evals.py
tests/test_evals_anthropic.py
tests/test_evals_comprehensive.py
tests/test_fixes_comprehensive.py
tests/test_flake_evals.py
tests/test_flake_evals_anthropic.py
tests/test_flake_search.py
tests/test_flake_search_improved.py
tests/test_flakes_stats_eval.py
tests/test_main.py
tests/test_mcp_behavior_comprehensive.py
tests/test_mcp_behavior_evals.py
tests/test_mcp_tools_comprehensive.py
tests/test_nixhub_evals.py
tests/test_nixhub_find_version.py
tests/test_nixhub_integration.py
tests/test_nixhub_real_integration.py
tests/test_nixos_info_option_evals.py
tests/test_nixos_option_info.py
tests/test_nixos_stats_regression.py
tests/test_option_info_improvements.py
tests/test_package_counts_eval.py
tests/test_plain_text_output.py
tests/test_real_integration.py
tests/test_real_world_scenarios.py
tests/test_server_comprehensive.py
mseep_mcp_nixos-1.0.0.dist-info/METADATA
mseep_mcp_nixos-1.0.0.dist-info/WHEEL
mseep_mcp_nixos-1.0.0.dist-info/top_level.txt
mseep_mcp_nixos-1.0.0.dist-info/RECORD
